<?xml version="1.0" ?><annotation>
	<folder>VOC2007</folder>
	<filename>IMG_1138_3.jpeg</filename>
	<path>/Users/huangsheng/Documents/JobProject/soil_detection/cropped_soil_images/IMG_1138_3.jpeg</path>
	<source>
		<database>Unknown</database>
	</source>
	<size>
		<width>992</width>
		<height>736</height>
		<depth>3</depth>
	</size>
	<segmented>0</segmented>
	<object>
		<name>block</name>
		<pose>Unspecified</pose>
		<truncated>0</truncated>
		<difficult>0</difficult>
		<bndbox>
			<xmin>313</xmin>
			<ymin>293</ymin>
			<xmax>511</xmax>
			<ymax>420</ymax>
		</bndbox>
	</object>
	<object>
		<name>block</name>
		<pose>Unspecified</pose>
		<truncated>0</truncated>
		<difficult>0</difficult>
		<bndbox>
			<xmin>117</xmin>
			<ymin>130</ymin>
			<xmax>283</xmax>
			<ymax>302</ymax>
		</bndbox>
	</object>
	<object>
		<name>block</name>
		<pose>Unspecified</pose>
		<truncated>0</truncated>
		<difficult>0</difficult>
		<bndbox>
			<xmin>342</xmin>
			<ymin>406</ymin>
			<xmax>461</xmax>
			<ymax>498</ymax>
		</bndbox>
	</object>
	<object>
		<name>block</name>
		<pose>Unspecified</pose>
		<truncated>0</truncated>
		<difficult>0</difficult>
		<bndbox>
			<xmin>350</xmin>
			<ymin>509</ymin>
			<xmax>463</xmax>
			<ymax>627</ymax>
		</bndbox>
	</object>
	<object>
		<name>block</name>
		<pose>Unspecified</pose>
		<truncated>0</truncated>
		<difficult>0</difficult>
		<bndbox>
			<xmin>601</xmin>
			<ymin>530</ymin>
			<xmax>711</xmax>
			<ymax>647</ymax>
		</bndbox>
	</object>
	<object>
		<name>block</name>
		<pose>Unspecified</pose>
		<truncated>0</truncated>
		<difficult>0</difficult>
		<bndbox>
			<xmin>529</xmin>
			<ymin>94</ymin>
			<xmax>634</xmax>
			<ymax>242</ymax>
		</bndbox>
	</object>
</annotation>