<?xml version="1.0" ?><annotation>
	<folder>VOC2007</folder>
	<filename>IMG_1110_4.jpeg</filename>
	<path>/Users/huangsheng/Documents/JobProject/soil_detection/cropped_soil_images/IMG_1110_4.jpeg</path>
	<source>
		<database>Unknown</database>
	</source>
	<size>
		<width>992</width>
		<height>736</height>
		<depth>3</depth>
	</size>
	<segmented>0</segmented>
	<object>
		<name>block</name>
		<pose>Unspecified</pose>
		<truncated>1</truncated>
		<difficult>0</difficult>
		<bndbox>
			<xmin>1</xmin>
			<ymin>320</ymin>
			<xmax>129</xmax>
			<ymax>486</ymax>
		</bndbox>
	</object>
	<object>
		<name>block</name>
		<pose>Unspecified</pose>
		<truncated>0</truncated>
		<difficult>0</difficult>
		<bndbox>
			<xmin>463</xmin>
			<ymin>464</ymin>
			<xmax>612</xmax>
			<ymax>618</ymax>
		</bndbox>
	</object>
	<object>
		<name>block</name>
		<pose>Unspecified</pose>
		<truncated>0</truncated>
		<difficult>0</difficult>
		<bndbox>
			<xmin>319</xmin>
			<ymin>136</ymin>
			<xmax>444</xmax>
			<ymax>293</ymax>
		</bndbox>
	</object>
	<object>
		<name>block</name>
		<pose>Unspecified</pose>
		<truncated>0</truncated>
		<difficult>0</difficult>
		<bndbox>
			<xmin>81</xmin>
			<ymin>76</ymin>
			<xmax>207</xmax>
			<ymax>190</ymax>
		</bndbox>
	</object>
</annotation>