<?xml version="1.0" ?><annotation>
	<folder>VOC2007</folder>
	<filename>IMG_1145_13.jpeg</filename>
	<path>/Users/huangsheng/Documents/JobProject/soil_detection/cropped_soil_images/IMG_1145_13.jpeg</path>
	<source>
		<database>Unknown</database>
	</source>
	<size>
		<width>992</width>
		<height>736</height>
		<depth>3</depth>
	</size>
	<segmented>0</segmented>
	<object>
		<name>block</name>
		<pose>Unspecified</pose>
		<truncated>0</truncated>
		<difficult>0</difficult>
		<bndbox>
			<xmin>264</xmin>
			<ymin>229</ymin>
			<xmax>399</xmax>
			<ymax>366</ymax>
		</bndbox>
	</object>
	<object>
		<name>block</name>
		<pose>Unspecified</pose>
		<truncated>0</truncated>
		<difficult>0</difficult>
		<bndbox>
			<xmin>675</xmin>
			<ymin>310</ymin>
			<xmax>791</xmax>
			<ymax>436</ymax>
		</bndbox>
	</object>
	<object>
		<name>block</name>
		<pose>Unspecified</pose>
		<truncated>0</truncated>
		<difficult>0</difficult>
		<bndbox>
			<xmin>392</xmin>
			<ymin>395</ymin>
			<xmax>510</xmax>
			<ymax>479</ymax>
		</bndbox>
	</object>
</annotation>