<?xml version="1.0" ?><annotation>
	<folder>VOC2007</folder>
	<filename>IMG_1154_6.jpeg</filename>
	<path>/Users/huangsheng/Documents/JobProject/soil_detection/cropped_soil_images/IMG_1154_6.jpeg</path>
	<source>
		<database>Unknown</database>
	</source>
	<size>
		<width>992</width>
		<height>736</height>
		<depth>3</depth>
	</size>
	<segmented>0</segmented>
	<object>
		<name>block</name>
		<pose>Unspecified</pose>
		<truncated>0</truncated>
		<difficult>0</difficult>
		<bndbox>
			<xmin>391</xmin>
			<ymin>343</ymin>
			<xmax>529</xmax>
			<ymax>449</ymax>
		</bndbox>
	</object>
	<object>
		<name>block</name>
		<pose>Unspecified</pose>
		<truncated>0</truncated>
		<difficult>0</difficult>
		<bndbox>
			<xmin>295</xmin>
			<ymin>370</ymin>
			<xmax>396</xmax>
			<ymax>508</ymax>
		</bndbox>
	</object>
	<object>
		<name>block</name>
		<pose>Unspecified</pose>
		<truncated>0</truncated>
		<difficult>0</difficult>
		<bndbox>
			<xmin>157</xmin>
			<ymin>303</ymin>
			<xmax>302</xmax>
			<ymax>458</ymax>
		</bndbox>
	</object>
	<object>
		<name>block</name>
		<pose>Unspecified</pose>
		<truncated>0</truncated>
		<difficult>0</difficult>
		<bndbox>
			<xmin>540</xmin>
			<ymin>413</ymin>
			<xmax>622</xmax>
			<ymax>487</ymax>
		</bndbox>
	</object>
	<object>
		<name>block</name>
		<pose>Unspecified</pose>
		<truncated>0</truncated>
		<difficult>0</difficult>
		<bndbox>
			<xmin>274</xmin>
			<ymin>94</ymin>
			<xmax>394</xmax>
			<ymax>174</ymax>
		</bndbox>
	</object>
	<object>
		<name>block</name>
		<pose>Unspecified</pose>
		<truncated>0</truncated>
		<difficult>0</difficult>
		<bndbox>
			<xmin>780</xmin>
			<ymin>289</ymin>
			<xmax>856</xmax>
			<ymax>382</ymax>
		</bndbox>
	</object>
</annotation>